broccoli_mwaa_fix/__init__.py
broccoli_mwaa_fix/broccoli.py
broccoli_mwaa_fix-0.10.dist-info/METADATA
broccoli_mwaa_fix-0.10.dist-info/WHEEL
broccoli_mwaa_fix-0.10.dist-info/top_level.txt
broccoli_mwaa_fix-0.10.dist-info/RECORD
