Metadata-Version: 2.1
Name: broccoli-mwaa-fix
Version: 0.10
Summary: broccoli_mwaa_fix
Author: Broccoli Squad
License: TBD
Requires-Dist: watchtower
